coauthor/__init__.py
coauthor/main.py
coauthor/config/tools/__init__.py
coauthor/config/tools/ansible.yml
coauthor/config/tools/generic.yml
coauthor/modules/__init__.py
coauthor/modules/ai.py
coauthor/modules/file_processor.py
coauthor/modules/file_scanner.py
coauthor/modules/file_watcher.py
coauthor/modules/jira_watcher.py
coauthor/modules/langgraph.py
coauthor/modules/markdown.py
coauthor/modules/plantuml.py
coauthor/modules/request_history.py
coauthor/modules/summary.py
coauthor/modules/tasks.py
coauthor/modules/tool_utils.py
coauthor/modules/web_tasks.py
coauthor/modules/workflow.py
coauthor/modules/workflow_tasks.py
coauthor/modules/youtube.py
coauthor/modules/tools/__init__.py
coauthor/modules/tools/ansible.py
coauthor/modules/tools/base.py
coauthor/modules/tools/generic.py
coauthor/profiles/ansible-collection/config.yml
coauthor/profiles/ansible-collection/examples/ansible-role-template.md
coauthor/profiles/ansible-collection/templates/ansible-collection/system.md
coauthor/profiles/ansible-collection/templates/ansible-collection/user.md
coauthor/profiles/ansible-collection/templates/ansible-collection-readme/system.md
coauthor/profiles/ansible-collection/templates/ansible-collection-readme/user.md
coauthor/profiles/ansible-collection/templates/module-doc/system.md
coauthor/profiles/ansible-collection/templates/module-doc/user.md
coauthor/profiles/ansible-collection/templates/module-doc/user/code.md
coauthor/profiles/ansible-collection/templates/modules-linux/system.md
coauthor/profiles/ansible-collection/templates/modules-linux/user.md
coauthor/profiles/ansible-collection/templates/modules-linux/user/git_remote.py
coauthor/profiles/ansible-collection/templates/modules-win/system.md
coauthor/profiles/ansible-collection/templates/modules-win/user.md
coauthor/profiles/ansible-collection/templates/modules-win/user/win_certificate.ps1
coauthor/profiles/ansible-collection/templates/role-meta-file/system.md
coauthor-0.1.6.dist-info/entry_points.txt
coauthor-0.1.6.dist-info/licenses/LICENSE
coauthor-0.1.6.dist-info/WHEEL
coauthor-0.1.6.dist-info/METADATA
coauthor-0.1.6.dist-info/RECORD
