Metadata-Version: 2.4
Name: coauthor
Version: 0.1.6
Summary: Coauthor Python Project
Author-email: Onno van der Straaten <onknows@c2platform.org>
Requires-Python: >=3.8.1
Classifier: Development Status :: 3 - Alpha
Classifier: Intended Audience :: Developers
Classifier: License :: OSI Approved :: MIT License
Classifier: Programming Language :: Python :: 3 :: Only
Classifier: Programming Language :: Python :: 3.10
Classifier: Programming Language :: Python :: 3.11
License-File: LICENSE
Requires-Dist: inotify_simple==1.3.5
Requires-Dist: openai==1.58.1
Requires-Dist: PyYAML==6.0.2
Requires-Dist: Jinja2==3.1.4
Requires-Dist: requests==2.32.3
Requires-Dist: duckduckgo_search==7.2.0
Requires-Dist: markdownify==0.14.1
Requires-Dist: beautifulsoup4==4.12.3
Requires-Dist: nest_asyncio==1.6.0
Requires-Dist: scikit-learn==1.6.0
Requires-Dist: pandas==2.2.3
Requires-Dist: pyarrow==18.1.0
Requires-Dist: ipython==8.31.0
Requires-Dist: youtube-transcript-api==1.0.3
Requires-Dist: google-api-python-client==2.170.0
Requires-Dist: jira==3.8.0
Requires-Dist: notify2==0.3.1
Requires-Dist: pyspark>=3.0.0 ; extra == "spark"
Requires-Dist: bandit[toml]==1.7.5 ; extra == "test"
Requires-Dist: black==23.3.0 ; extra == "test"
Requires-Dist: check-manifest==0.49 ; extra == "test"
Requires-Dist: flake8-bugbear==23.5.9 ; extra == "test"
Requires-Dist: flake8-docstrings ; extra == "test"
Requires-Dist: flake8-formatter_junit_xml ; extra == "test"
Requires-Dist: flake8 ; extra == "test"
Requires-Dist: flake8-pyproject ; extra == "test"
Requires-Dist: pre-commit==3.3.1 ; extra == "test"
Requires-Dist: pylint==2.17.4 ; extra == "test"
Requires-Dist: pylint_junit ; extra == "test"
Requires-Dist: pytest-cov==4.0.0 ; extra == "test"
Requires-Dist: pytest-mock<3.10.1 ; extra == "test"
Requires-Dist: pytest-runner ; extra == "test"
Requires-Dist: pytest==7.3.1 ; extra == "test"
Requires-Dist: pytest-github-actions-annotate-failures ; extra == "test"
Requires-Dist: shellcheck-py==0.9.0.2 ; extra == "test"
Project-URL: Documentation, https://coauthor.readthedocs.io
Project-URL: Source, https://gitlab.com/c2platform/c2/coauthor/
Project-URL: Tracker, https://gitlab.com/c2platform/c2/coauthor/-/issues
Provides-Extra: spark
Provides-Extra: test
